README.md
setup.py
sv_utils/__init__.py
sv_utils/annotation.py
sv_utils/filter.py
sv_utils/header_info.py
sv_utils/homology.py
sv_utils/mutation.py
sv_utils/my_seq.py
sv_utils/nonB_DB.py
sv_utils/parser.py
sv_utils/run.py
sv_utils/simple_repeat.py
sv_utils/utils.py
sv_utils/version.py
sv_utils.egg-info/PKG-INFO
sv_utils.egg-info/SOURCES.txt
sv_utils.egg-info/dependency_links.txt
sv_utils.egg-info/entry_points.txt
sv_utils.egg-info/top_level.txt
sv_utils/data/fusion_db.txt